api_list_pagination/__init__.py
api_list_pagination/api_list_pagination.py
api_list_pagination-0.0.2.dist-info/LICENSE
api_list_pagination-0.0.2.dist-info/METADATA
api_list_pagination-0.0.2.dist-info/WHEEL
api_list_pagination-0.0.2.dist-info/top_level.txt
api_list_pagination-0.0.2.dist-info/RECORD
