Metadata-Version: 2.2
Name: api_list_pagination
Version: 0.0.2
Summary: A small package for easy use list apis in django rest framework, I call this ALP.
Maintainer-email: Mho3ein <hh.vaez@gmail.com>
Project-URL: Homepage, https://github.com/mho3en/api_list_pagination
Project-URL: Issues, https://github.com/mho3en/api_list_pagination/issues
Classifier: Programming Language :: Python :: 3
Classifier: License :: OSI Approved :: MIT License
Classifier: Operating System :: OS Independent
Requires-Python: >=3.8
License-File: LICENSE
Requires-Dist: djangorestframework
